linked_list_vf/__init__.py
linked_list_vf/linked_list.py
linked_list_vf-0.0.1.dist-info/LICENSE
linked_list_vf-0.0.1.dist-info/METADATA
linked_list_vf-0.0.1.dist-info/WHEEL
linked_list_vf-0.0.1.dist-info/top_level.txt
linked_list_vf-0.0.1.dist-info/RECORD
