Metadata-Version: 2.1
Name: linked-list-vf
Version: 0.0.1
Summary: All is in the title ^^
Home-page: https://github.com/pypa/sampleproject
Author: Venodez
Author-email: Valentin.Enzo@outlook.fr
License: UNKNOWN
Platform: UNKNOWN
Classifier: Programming Language :: Python :: 3
Classifier: License :: OSI Approved :: MIT License
Classifier: Operating System :: OS Independent
Requires-Python: >=3.6
